setup.py
src/digimat/__init__.py
src/digimat.lp.egg-info/PKG-INFO
src/digimat.lp.egg-info/SOURCES.txt
src/digimat.lp.egg-info/dependency_links.txt
src/digimat.lp.egg-info/namespace_packages.txt
src/digimat.lp.egg-info/not-zip-safe
src/digimat.lp.egg-info/requires.txt
src/digimat.lp.egg-info/top_level.txt
src/digimat/lp/__init__.py
src/digimat/lp/lanpacket.py