Metadata-Version: 1.0
Name: digimat.lp
Version: 0.1.1
Summary: Digimat LanPacket
Home-page: UNKNOWN
Author: Frederic Hess
Author-email: fhess@splust.ch
License: PSF
Platform: UNKNOWN
